_duckdb.cpython-312-x86_64-linux-gnu.so
_duckdb-stubs/__init__.pyi
_duckdb-stubs/_func.pyi
_duckdb-stubs/_sqltypes.pyi
adbc_driver_duckdb/__init__.py
adbc_driver_duckdb/dbapi.py
quacklab/__init__.py
quacklab/_dbapi_type_object.py
quacklab/_version.py
quacklab/bytes_io_wrapper.py
quacklab/filesystem.py
quacklab/polars_io.py
quacklab/py.typed
quacklab/udf.py
quacklab/experimental/__init__.py
quacklab/experimental/spark/LICENSE
quacklab/experimental/spark/__init__.py
quacklab/experimental/spark/_globals.py
quacklab/experimental/spark/_typing.py
quacklab/experimental/spark/conf.py
quacklab/experimental/spark/context.py
quacklab/experimental/spark/exception.py
quacklab/experimental/spark/errors/__init__.py
quacklab/experimental/spark/errors/error_classes.py
quacklab/experimental/spark/errors/utils.py
quacklab/experimental/spark/errors/exceptions/__init__.py
quacklab/experimental/spark/errors/exceptions/base.py
quacklab/experimental/spark/sql/__init__.py
quacklab/experimental/spark/sql/_typing.py
quacklab/experimental/spark/sql/catalog.py
quacklab/experimental/spark/sql/column.py
quacklab/experimental/spark/sql/conf.py
quacklab/experimental/spark/sql/dataframe.py
quacklab/experimental/spark/sql/functions.py
quacklab/experimental/spark/sql/group.py
quacklab/experimental/spark/sql/readwriter.py
quacklab/experimental/spark/sql/session.py
quacklab/experimental/spark/sql/streaming.py
quacklab/experimental/spark/sql/type_utils.py
quacklab/experimental/spark/sql/types.py
quacklab/experimental/spark/sql/udf.py
quacklab/func/__init__.py
quacklab/functional/__init__.py
quacklab/query_graph/__main__.py
quacklab/sqltypes/__init__.py
quacklab/typing/__init__.py
quacklab/value/__init__.py
quacklab/value/constant/__init__.py
quacklab-1.4.1.dist-info/METADATA
quacklab-1.4.1.dist-info/WHEEL
quacklab-1.4.1.dist-info/RECORD
quacklab-1.4.1.dist-info/licenses/LICENSE
